sentinels/__init__.py
sentinels/__version__.py
sentinels-1.1.0.dist-info/METADATA
sentinels-1.1.0.dist-info/WHEEL
sentinels-1.1.0.dist-info/licenses/LICENSE
sentinels-1.1.0.dist-info/RECORD
