Metadata-Version: 2.4
Name: sentinels
Version: 1.1.0
Summary: Various objects to denote special meanings in python
Project-URL: Homepage, https://github.com/vmalloc/sentinels
Author-email: Rotem Yaari <vmalloc@gmail.com>
License: BSD 3-Clause License
License-File: LICENSE
Classifier: Programming Language :: Python :: 3.9
Classifier: Programming Language :: Python :: 3.10
Classifier: Programming Language :: Python :: 3.11
Classifier: Programming Language :: Python :: 3.12
Classifier: Programming Language :: Python :: 3.13
Requires-Python: >=3.9
Provides-Extra: testing
Requires-Dist: pylint; extra == 'testing'
Requires-Dist: pytest; extra == 'testing'
